Metadata-Version: 2.1
Name: tredparse
Version: 1.1.12
Summary: Short Tandem Repeat (STR) genotyper
Home-page: https://github.com/tanghaibao/tredparse
Author: Haibao Tang, Smriti Ramakrishnan
Author-email: tanghaibao@gmail.com
License: HLI open source license
Platform: UNKNOWN
Classifier: Development Status :: 4 - Beta
Classifier: Intended Audience :: Science/Research
Classifier: License :: OSI Approved :: BSD License
Classifier: Programming Language :: Python
Classifier: Programming Language :: Python :: 3
Classifier: Topic :: Scientific/Engineering :: Bio-Informatics
License-File: LICENSE
